MANIFEST.in
setup.py
docs/CONTRIBUTORS.txt
docs/HISTORY.txt
docs/LICENSE.ZPL
docs/LICENSE.txt
docs/README.txt
src/ztfy/__init__.py
src/ztfy.base.egg-info/PKG-INFO
src/ztfy.base.egg-info/SOURCES.txt
src/ztfy.base.egg-info/dependency_links.txt
src/ztfy.base.egg-info/entry_points.txt
src/ztfy.base.egg-info/namespace_packages.txt
src/ztfy.base.egg-info/not-zip-safe
src/ztfy.base.egg-info/requires.txt
src/ztfy.base.egg-info/top_level.txt
src/ztfy/base/__init__.py
src/ztfy/base/configure.zcml
src/ztfy/base/index.py
src/ztfy/base/oid.py
src/ztfy/base/ordered.py
src/ztfy/base/path.py
src/ztfy/base/schema.py
src/ztfy/base/zodb.py
src/ztfy/base/doctests/README.txt
src/ztfy/base/interfaces/__init__.py
src/ztfy/base/interfaces/container.py
src/ztfy/base/locales/ztfy.base.pot
src/ztfy/base/locales/en/LC_MESSAGES/ztfy.base.mo
src/ztfy/base/locales/en/LC_MESSAGES/ztfy.base.po
src/ztfy/base/locales/en/LC_MESSAGES/ztfy.base.po~
src/ztfy/base/locales/fr/LC_MESSAGES/ztfy.base.mo
src/ztfy/base/locales/fr/LC_MESSAGES/ztfy.base.po
src/ztfy/base/locales/fr/LC_MESSAGES/ztfy.base.po~
src/ztfy/base/tests/__init__.py
src/ztfy/base/tests/test_docs.py
src/ztfy/base/tests/test_docstrings.py