Metadata-Version: 1.1
Name: ztfy.base
Version: 0.1.2
Summary: ZTFY base content classes
Home-page: http://hg.ztfy.org/ztfy.base
Author: Thierry Florac
Author-email: tflorac@ulthar.net
License: zpl
Keywords: ZTFY content
Platform: UNKNOWN
Classifier: Programming Language :: Python
